rs_vector_db-0.1.4.dist-info/METADATA
rs_vector_db-0.1.4.dist-info/WHEEL
rs_vector_db.libs/libcrypto-53eaadd0.so.3
rs_vector_db.libs/libssl-0fe501d2.so.3
rs_vector_db/__init__.py
rs_vector_db/rs_vector_db.cpython-311-x86_64-linux-gnu.so
rs_vector_db-0.1.4.dist-info/RECORD
